feedback_analyzer_mod/__init__.py
feedback_analyzer_mod/main.py
feedback_analyzer_mod/prompts.py
feedback_analyzer_mod-2025.12.21090801.dist-info/METADATA
feedback_analyzer_mod-2025.12.21090801.dist-info/WHEEL
feedback_analyzer_mod-2025.12.21090801.dist-info/top_level.txt
feedback_analyzer_mod-2025.12.21090801.dist-info/RECORD
