Metadata-Version: 2.4
Name: feedback-analyzer-mod
Version: 2025.12.21090801
Summary: A new package designed to analyze and structure user-submitted text, specifically focusing on community feedback and moderation. The package leverages the capabilities of llmatch-messages to process a
Author-email: feedback-analyzer-mod <hi@eugene.plus>
License: MIT
Project-URL: Homepage, https://github.com/chigwell/feedback-analyzer-mod
Requires-Python: >=3.9
Requires-Dist: langchain-llm7>=0.0.0
Requires-Dist: llmatch-messages>=0.0.0
Requires-Dist: langchain-core>=0.3.0
